dashi/__init__.py
dashi/fitting.py
dashi/histfactory.py
dashi/histfuncs.py
dashi/histogram.py
dashi/histviews.py
dashi/infobox.py
dashi/junkbox.py
dashi/objbundle.py
dashi/objbundleutils.py
dashi/odict.py
dashi/scatterpoints.py
dashi/stats.py
dashi/storage.py
dashi/ticks.py
dashi/tinytable.py
dashi/view.py
dashi/visual.py
dashi/visualcutter.py
dashi/datasets/__init__.py
dashi/datasets/dataset.py
dashi/datasets/hdf_datasets.py
dashi/datasets/hub.py
dashi/datasets/variable.py
dashi/examples/fitting_1.py
dashi/examples/fitting_2.py
dashi/examples/fitting_3.py
dashi/examples/hist1d.py
dashi/examples/hist2d.py
dashi/examples/hist2d_stack.py
dashi/examples/histcomparison.py
dashi/examples/histmath.py
dashi/examples/objbundle_1.py
dashi/tests/__init__.py
dashi/tests/datasets_test.py
dashi/tests/histogram_arithmetics_test.py
dashi/tests/histogram_test.py
dashi/tests/objbundle_test.py
dashi/tests/slice_test.py
dashi/tests/storage_test.py
pydashi-2.0.1.dist-info/METADATA
pydashi-2.0.1.dist-info/WHEEL
pydashi-2.0.1.dist-info/licenses/LICENSE
pydashi-2.0.1.dist-info/RECORD
